{
  "$schema": "https://raw.githubusercontent.com/spdx/spdx-spec/v2.2.1/schemas/spdx-schema.json",
  "spdxVersion": "SPDX-2.2",
  "dataLicense": "CC0-1.0",
  "SPDXID": "SPDXRef-DOCUMENT",
  "documentNamespace": "https://spdx.org/spdxdocs/libjpeg-turbo-x64-windows-3.0.1-a68a565b-74ef-45e3-9ddd-d10e4a0e42d4",
  "name": "libjpeg-turbo:x64-windows@3.0.1 229d368e77c18517875fce2fd32cf71d68bf2fcc548be51e94b565a216d07191",
  "creationInfo": {
    "creators": [
      "Tool: vcpkg-2026-03-04-4b3e4c276b5b87a649e66341e11553e8c577459c"
    ],
    "created": "2026-03-24T13:30:51Z"
  },
  "relationships": [
    {
      "spdxElementId": "SPDXRef-port",
      "relationshipType": "GENERATES",
      "relatedSpdxElement": "SPDXRef-binary"
    },
    {
      "spdxElementId": "SPDXRef-port",
      "relationshipType": "CONTAINS",
      "relatedSpdxElement": "SPDXRef-port-file-0"
    },
    {
      "spdxElementId": "SPDXRef-port",
      "relationshipType": "CONTAINS",
      "relatedSpdxElement": "SPDXRef-port-file-1"
    },
    {
      "spdxElementId": "SPDXRef-port",
      "relationshipType": "CONTAINS",
      "relatedSpdxElement": "SPDXRef-port-file-2"
    },
    {
      "spdxElementId": "SPDXRef-port",
      "relationshipType": "CONTAINS",
      "relatedSpdxElement": "SPDXRef-port-file-3"
    },
    {
      "spdxElementId": "SPDXRef-port",
      "relationshipType": "CONTAINS",
      "relatedSpdxElement": "SPDXRef-port-file-4"
    },
    {
      "spdxElementId": "SPDXRef-port-file-4",
      "relationshipType": "DEPENDENCY_MANIFEST_OF",
      "relatedSpdxElement": "SPDXRef-port"
    },
    {
      "spdxElementId": "SPDXRef-port",
      "relationshipType": "CONTAINS",
      "relatedSpdxElement": "SPDXRef-port-file-5"
    },
    {
      "spdxElementId": "SPDXRef-binary",
      "relationshipType": "CONTAINS",
      "relatedSpdxElement": "SPDXRef-binary-file-0"
    },
    {
      "spdxElementId": "SPDXRef-binary",
      "relationshipType": "CONTAINS",
      "relatedSpdxElement": "SPDXRef-binary-file-1"
    },
    {
      "spdxElementId": "SPDXRef-binary",
      "relationshipType": "CONTAINS",
      "relatedSpdxElement": "SPDXRef-binary-file-2"
    },
    {
      "spdxElementId": "SPDXRef-binary",
      "relationshipType": "CONTAINS",
      "relatedSpdxElement": "SPDXRef-binary-file-3"
    },
    {
      "spdxElementId": "SPDXRef-binary",
      "relationshipType": "CONTAINS",
      "relatedSpdxElement": "SPDXRef-binary-file-4"
    },
    {
      "spdxElementId": "SPDXRef-binary",
      "relationshipType": "CONTAINS",
      "relatedSpdxElement": "SPDXRef-binary-file-5"
    },
    {
      "spdxElementId": "SPDXRef-binary",
      "relationshipType": "CONTAINS",
      "relatedSpdxElement": "SPDXRef-binary-file-6"
    },
    {
      "spdxElementId": "SPDXRef-binary",
      "relationshipType": "CONTAINS",
      "relatedSpdxElement": "SPDXRef-binary-file-7"
    },
    {
      "spdxElementId": "SPDXRef-binary",
      "relationshipType": "CONTAINS",
      "relatedSpdxElement": "SPDXRef-binary-file-8"
    },
    {
      "spdxElementId": "SPDXRef-binary",
      "relationshipType": "CONTAINS",
      "relatedSpdxElement": "SPDXRef-binary-file-9"
    },
    {
      "spdxElementId": "SPDXRef-binary",
      "relationshipType": "CONTAINS",
      "relatedSpdxElement": "SPDXRef-binary-file-10"
    },
    {
      "spdxElementId": "SPDXRef-binary",
      "relationshipType": "CONTAINS",
      "relatedSpdxElement": "SPDXRef-binary-file-11"
    },
    {
      "spdxElementId": "SPDXRef-binary",
      "relationshipType": "CONTAINS",
      "relatedSpdxElement": "SPDXRef-binary-file-12"
    },
    {
      "spdxElementId": "SPDXRef-binary",
      "relationshipType": "CONTAINS",
      "relatedSpdxElement": "SPDXRef-binary-file-13"
    },
    {
      "spdxElementId": "SPDXRef-binary",
      "relationshipType": "CONTAINS",
      "relatedSpdxElement": "SPDXRef-binary-file-14"
    },
    {
      "spdxElementId": "SPDXRef-binary",
      "relationshipType": "CONTAINS",
      "relatedSpdxElement": "SPDXRef-binary-file-15"
    },
    {
      "spdxElementId": "SPDXRef-binary",
      "relationshipType": "CONTAINS",
      "relatedSpdxElement": "SPDXRef-binary-file-16"
    },
    {
      "spdxElementId": "SPDXRef-binary",
      "relationshipType": "CONTAINS",
      "relatedSpdxElement": "SPDXRef-binary-file-17"
    },
    {
      "spdxElementId": "SPDXRef-binary",
      "relationshipType": "CONTAINS",
      "relatedSpdxElement": "SPDXRef-binary-file-18"
    },
    {
      "spdxElementId": "SPDXRef-binary",
      "relationshipType": "CONTAINS",
      "relatedSpdxElement": "SPDXRef-binary-file-19"
    },
    {
      "spdxElementId": "SPDXRef-binary",
      "relationshipType": "CONTAINS",
      "relatedSpdxElement": "SPDXRef-binary-file-20"
    },
    {
      "spdxElementId": "SPDXRef-binary",
      "relationshipType": "CONTAINS",
      "relatedSpdxElement": "SPDXRef-binary-file-21"
    },
    {
      "spdxElementId": "SPDXRef-binary",
      "relationshipType": "CONTAINS",
      "relatedSpdxElement": "SPDXRef-binary-file-22"
    },
    {
      "spdxElementId": "SPDXRef-binary",
      "relationshipType": "CONTAINS",
      "relatedSpdxElement": "SPDXRef-binary-file-23"
    },
    {
      "spdxElementId": "SPDXRef-binary",
      "relationshipType": "CONTAINS",
      "relatedSpdxElement": "SPDXRef-binary-file-24"
    },
    {
      "spdxElementId": "SPDXRef-binary",
      "relationshipType": "CONTAINS",
      "relatedSpdxElement": "SPDXRef-binary-file-25"
    },
    {
      "spdxElementId": "SPDXRef-binary",
      "relationshipType": "CONTAINS",
      "relatedSpdxElement": "SPDXRef-binary-file-26"
    },
    {
      "spdxElementId": "SPDXRef-binary",
      "relationshipType": "CONTAINS",
      "relatedSpdxElement": "SPDXRef-binary-file-27"
    },
    {
      "spdxElementId": "SPDXRef-binary",
      "relationshipType": "CONTAINS",
      "relatedSpdxElement": "SPDXRef-binary-file-28"
    },
    {
      "spdxElementId": "SPDXRef-binary",
      "relationshipType": "CONTAINS",
      "relatedSpdxElement": "SPDXRef-binary-file-29"
    }
  ],
  "packages": [
    {
      "name": "libjpeg-turbo",
      "SPDXID": "SPDXRef-port",
      "versionInfo": "3.0.1",
      "downloadLocation": "git+https://github.com/microsoft/vcpkg@481b08127d4002ba7441f144df259e03271e7592",
      "homepage": "https://github.com/libjpeg-turbo/libjpeg-turbo",
      "licenseConcluded": "BSD-3-Clause",
      "licenseDeclared": "NOASSERTION",
      "copyrightText": "NOASSERTION",
      "description": "libjpeg-turbo is a JPEG image codec that uses SIMD instructions (MMX, SSE2, NEON, AltiVec) to accelerate baseline JPEG compression and decompression on x86, x86-64, ARM, and PowerPC systems.",
      "comment": "This is the port (recipe) consumed by vcpkg."
    },
    {
      "name": "libjpeg-turbo:x64-windows",
      "SPDXID": "SPDXRef-binary",
      "versionInfo": "229d368e77c18517875fce2fd32cf71d68bf2fcc548be51e94b565a216d07191",
      "downloadLocation": "NONE",
      "licenseConcluded": "BSD-3-Clause",
      "licenseDeclared": "NOASSERTION",
      "copyrightText": "NOASSERTION",
      "comment": "This is a binary package built by vcpkg."
    },
    {
      "SPDXID": "SPDXRef-resource-0",
      "name": "libjpeg-turbo/libjpeg-turbo",
      "downloadLocation": "git+https://github.com/libjpeg-turbo/libjpeg-turbo@3.0.1",
      "licenseConcluded": "NOASSERTION",
      "licenseDeclared": "NOASSERTION",
      "copyrightText": "NOASSERTION",
      "checksums": [
        {
          "algorithm": "SHA512",
          "checksumValue": "6f9f384bb3bf5476935b313576c03f11d3e22bf727aa135eb840a2c9b994890e6712e23f25996b91ee901e8242b41100fb8c3cb4905ffb72776edf14b2c05a12"
        }
      ]
    }
  ],
  "files": [
    {
      "fileName": "./add-options-for-exes-docs-headers.patch",
      "SPDXID": "SPDXRef-port-file-0",
      "checksums": [
        {
          "algorithm": "SHA256",
          "checksumValue": "cdba08596112a6fd0069dcd252bea7d081a388e9044426574a818bb6a98c48e7"
        }
      ],
      "licenseConcluded": "NOASSERTION",
      "copyrightText": "NOASSERTION"
    },
    {
      "fileName": "./portfile.cmake",
      "SPDXID": "SPDXRef-port-file-1",
      "checksums": [
        {
          "algorithm": "SHA256",
          "checksumValue": "834a4774207528900de4b6f7928fbc9e5c72cc2b7f2415e6f699bf8c48c19271"
        }
      ],
      "licenseConcluded": "NOASSERTION",
      "copyrightText": "NOASSERTION"
    },
    {
      "fileName": "./usage",
      "SPDXID": "SPDXRef-port-file-2",
      "checksums": [
        {
          "algorithm": "SHA256",
          "checksumValue": "f6ff243d0aba5bc85904527de17fc8a341a3568b0b19e3ac63b95029125b9e68"
        }
      ],
      "licenseConcluded": "NOASSERTION",
      "copyrightText": "NOASSERTION"
    },
    {
      "fileName": "./vcpkg-cmake-wrapper.cmake",
      "SPDXID": "SPDXRef-port-file-3",
      "checksums": [
        {
          "algorithm": "SHA256",
          "checksumValue": "d257c0a541dd60c4b6eb6f46a5e9f128a64a6ec40f3b8b5bc8ab753e7a935c61"
        }
      ],
      "licenseConcluded": "NOASSERTION",
      "copyrightText": "NOASSERTION"
    },
    {
      "fileName": "./vcpkg.json",
      "SPDXID": "SPDXRef-port-file-4",
      "checksums": [
        {
          "algorithm": "SHA256",
          "checksumValue": "3adef90d8f417df6a00220c881ee80f73e7854a4701505a924f81c0ac3d75f35"
        }
      ],
      "licenseConcluded": "NOASSERTION",
      "copyrightText": "NOASSERTION"
    },
    {
      "fileName": "./workaround_cmake_system_processor.patch",
      "SPDXID": "SPDXRef-port-file-5",
      "checksums": [
        {
          "algorithm": "SHA256",
          "checksumValue": "99378f41a1f50dc45967068b2d5c72abbc86285aae2f90c2d8be5061831724aa"
        }
      ],
      "licenseConcluded": "NOASSERTION",
      "copyrightText": "NOASSERTION"
    },
    {
      "fileName": "./bin/jpeg62.dll",
      "SPDXID": "SPDXRef-binary-file-0",
      "checksums": [
        {
          "algorithm": "SHA256",
          "checksumValue": "45b802f2be4b906352131b36687eaaf9c02733ec4fea5774d754b9c37545b9e4"
        }
      ],
      "licenseConcluded": "NOASSERTION",
      "copyrightText": "NOASSERTION"
    },
    {
      "fileName": "./bin/jpeg62.pdb",
      "SPDXID": "SPDXRef-binary-file-1",
      "checksums": [
        {
          "algorithm": "SHA256",
          "checksumValue": "e19cbe206d9d9c54630f549b1223203df0d7a6a3fa350274692a8f9af6dc3762"
        }
      ],
      "licenseConcluded": "NOASSERTION",
      "copyrightText": "NOASSERTION"
    },
    {
      "fileName": "./bin/turbojpeg.dll",
      "SPDXID": "SPDXRef-binary-file-2",
      "checksums": [
        {
          "algorithm": "SHA256",
          "checksumValue": "9dbcbc4c0c0894bc4724a99369c0537e87af8a51e2610bbcf0202b7232345551"
        }
      ],
      "licenseConcluded": "NOASSERTION",
      "copyrightText": "NOASSERTION"
    },
    {
      "fileName": "./bin/turbojpeg.pdb",
      "SPDXID": "SPDXRef-binary-file-3",
      "checksums": [
        {
          "algorithm": "SHA256",
          "checksumValue": "346f7bdc5bd9124d64d1a7489522ee8ba5e0615d2b6d6d14806e6f039a72a484"
        }
      ],
      "licenseConcluded": "NOASSERTION",
      "copyrightText": "NOASSERTION"
    },
    {
      "fileName": "./BUILD_INFO",
      "SPDXID": "SPDXRef-binary-file-4",
      "checksums": [
        {
          "algorithm": "SHA256",
          "checksumValue": "5e7f821ab4eb804deb535baa7b41edca682d0303cf21a91908c98d5c9a7dcf4d"
        }
      ],
      "licenseConcluded": "NOASSERTION",
      "copyrightText": "NOASSERTION"
    },
    {
      "fileName": "./debug/bin/jpeg62.dll",
      "SPDXID": "SPDXRef-binary-file-5",
      "checksums": [
        {
          "algorithm": "SHA256",
          "checksumValue": "ed1ea6d16919a92f0d5a81c1d0a3399942518e8c1b4391a58cec1a5b54d1b3cf"
        }
      ],
      "licenseConcluded": "NOASSERTION",
      "copyrightText": "NOASSERTION"
    },
    {
      "fileName": "./debug/bin/jpeg62.pdb",
      "SPDXID": "SPDXRef-binary-file-6",
      "checksums": [
        {
          "algorithm": "SHA256",
          "checksumValue": "90dd64575520c1591ef1a8dd3521d1790fac06307f3aee3e0c7a808478b2d769"
        }
      ],
      "licenseConcluded": "NOASSERTION",
      "copyrightText": "NOASSERTION"
    },
    {
      "fileName": "./debug/bin/turbojpeg.dll",
      "SPDXID": "SPDXRef-binary-file-7",
      "checksums": [
        {
          "algorithm": "SHA256",
          "checksumValue": "1a0298b80622cfaae7285a172af5140055c9e4351032bbbf81beebae132a93dd"
        }
      ],
      "licenseConcluded": "NOASSERTION",
      "copyrightText": "NOASSERTION"
    },
    {
      "fileName": "./debug/bin/turbojpeg.pdb",
      "SPDXID": "SPDXRef-binary-file-8",
      "checksums": [
        {
          "algorithm": "SHA256",
          "checksumValue": "7b65a0a8d069b29fe13ddd385b2c5e68140fc0611f961c06124074d0504dff8e"
        }
      ],
      "licenseConcluded": "NOASSERTION",
      "copyrightText": "NOASSERTION"
    },
    {
      "fileName": "./debug/lib/jpeg.lib",
      "SPDXID": "SPDXRef-binary-file-9",
      "checksums": [
        {
          "algorithm": "SHA256",
          "checksumValue": "333dcadaabf5a61eeaeb44be5e1d64d23219b992a843f8a8f7975d749b1345cd"
        }
      ],
      "licenseConcluded": "NOASSERTION",
      "copyrightText": "NOASSERTION"
    },
    {
      "fileName": "./debug/lib/pkgconfig/libjpeg.pc",
      "SPDXID": "SPDXRef-binary-file-10",
      "checksums": [
        {
          "algorithm": "SHA256",
          "checksumValue": "a7e997393ad0ca339d1d08a8fc3fe43582a6609ebf7b87b2050f9b6e796857a4"
        }
      ],
      "licenseConcluded": "NOASSERTION",
      "copyrightText": "NOASSERTION"
    },
    {
      "fileName": "./debug/lib/pkgconfig/libturbojpeg.pc",
      "SPDXID": "SPDXRef-binary-file-11",
      "checksums": [
        {
          "algorithm": "SHA256",
          "checksumValue": "1531f5524f997f2441fd9fe3e497e5fac14ab536e7e995ada30b3fea19f95c82"
        }
      ],
      "licenseConcluded": "NOASSERTION",
      "copyrightText": "NOASSERTION"
    },
    {
      "fileName": "./debug/lib/turbojpeg.lib",
      "SPDXID": "SPDXRef-binary-file-12",
      "checksums": [
        {
          "algorithm": "SHA256",
          "checksumValue": "4fa453c12ffd4a039b0a80fca45727d8212be274c658408ca82d93cf358f6353"
        }
      ],
      "licenseConcluded": "NOASSERTION",
      "copyrightText": "NOASSERTION"
    },
    {
      "fileName": "./include/jconfig.h",
      "SPDXID": "SPDXRef-binary-file-13",
      "checksums": [
        {
          "algorithm": "SHA256",
          "checksumValue": "f0d55e6fe017500d5d20bcf81fedfddd0811891320686d6558ec7f23079a0c9f"
        }
      ],
      "licenseConcluded": "NOASSERTION",
      "copyrightText": "NOASSERTION"
    },
    {
      "fileName": "./include/jerror.h",
      "SPDXID": "SPDXRef-binary-file-14",
      "checksums": [
        {
          "algorithm": "SHA256",
          "checksumValue": "30b21147dbfafbfde0fae378bf5ed1da379795a0e98938b92e7564f175c1a660"
        }
      ],
      "licenseConcluded": "NOASSERTION",
      "copyrightText": "NOASSERTION"
    },
    {
      "fileName": "./include/jmorecfg.h",
      "SPDXID": "SPDXRef-binary-file-15",
      "checksums": [
        {
          "algorithm": "SHA256",
          "checksumValue": "80a97f45ecb28d83310247eecec2a3865b5fd39ba0ecc490b48a36fac6318e26"
        }
      ],
      "licenseConcluded": "NOASSERTION",
      "copyrightText": "NOASSERTION"
    },
    {
      "fileName": "./include/jpeglib.h",
      "SPDXID": "SPDXRef-binary-file-16",
      "checksums": [
        {
          "algorithm": "SHA256",
          "checksumValue": "9e5f30f70c1fad9290328ca4a44825af9787787a8e11d73c00186005a66e239d"
        }
      ],
      "licenseConcluded": "NOASSERTION",
      "copyrightText": "NOASSERTION"
    },
    {
      "fileName": "./include/turbojpeg.h",
      "SPDXID": "SPDXRef-binary-file-17",
      "checksums": [
        {
          "algorithm": "SHA256",
          "checksumValue": "247e229441e026db69814a1b1ecae76ee914b1468f155441bf5a538c24edbe44"
        }
      ],
      "licenseConcluded": "NOASSERTION",
      "copyrightText": "NOASSERTION"
    },
    {
      "fileName": "./lib/jpeg.lib",
      "SPDXID": "SPDXRef-binary-file-18",
      "checksums": [
        {
          "algorithm": "SHA256",
          "checksumValue": "333dcadaabf5a61eeaeb44be5e1d64d23219b992a843f8a8f7975d749b1345cd"
        }
      ],
      "licenseConcluded": "NOASSERTION",
      "copyrightText": "NOASSERTION"
    },
    {
      "fileName": "./lib/pkgconfig/libjpeg.pc",
      "SPDXID": "SPDXRef-binary-file-19",
      "checksums": [
        {
          "algorithm": "SHA256",
          "checksumValue": "a0e60959ac6b6059db50a2ebcc89e55a29859a5dffd75f99be28cbbe9e99786a"
        }
      ],
      "licenseConcluded": "NOASSERTION",
      "copyrightText": "NOASSERTION"
    },
    {
      "fileName": "./lib/pkgconfig/libturbojpeg.pc",
      "SPDXID": "SPDXRef-binary-file-20",
      "checksums": [
        {
          "algorithm": "SHA256",
          "checksumValue": "f4812a67b2d91fbbaaefca81de363e9b42d84bda0e07bf94533fc0a20c2efca0"
        }
      ],
      "licenseConcluded": "NOASSERTION",
      "copyrightText": "NOASSERTION"
    },
    {
      "fileName": "./lib/turbojpeg.lib",
      "SPDXID": "SPDXRef-binary-file-21",
      "checksums": [
        {
          "algorithm": "SHA256",
          "checksumValue": "4fa453c12ffd4a039b0a80fca45727d8212be274c658408ca82d93cf358f6353"
        }
      ],
      "licenseConcluded": "NOASSERTION",
      "copyrightText": "NOASSERTION"
    },
    {
      "fileName": "./share/jpeg/vcpkg-cmake-wrapper.cmake",
      "SPDXID": "SPDXRef-binary-file-22",
      "checksums": [
        {
          "algorithm": "SHA256",
          "checksumValue": "d257c0a541dd60c4b6eb6f46a5e9f128a64a6ec40f3b8b5bc8ab753e7a935c61"
        }
      ],
      "licenseConcluded": "NOASSERTION",
      "copyrightText": "NOASSERTION"
    },
    {
      "fileName": "./share/libjpeg-turbo/copyright",
      "SPDXID": "SPDXRef-binary-file-23",
      "checksums": [
        {
          "algorithm": "SHA256",
          "checksumValue": "60c756742db3ad1913304e8b13f0e86e22e51adb50cc0b3333c163f7e45ceec1"
        }
      ],
      "licenseConcluded": "NOASSERTION",
      "copyrightText": "NOASSERTION"
    },
    {
      "fileName": "./share/libjpeg-turbo/libjpeg-turboConfig.cmake",
      "SPDXID": "SPDXRef-binary-file-24",
      "checksums": [
        {
          "algorithm": "SHA256",
          "checksumValue": "2f5f7122db44bb3f41a2c31a60475893f84f6e4d5c0afb080c6c160ee9f43fb9"
        }
      ],
      "licenseConcluded": "NOASSERTION",
      "copyrightText": "NOASSERTION"
    },
    {
      "fileName": "./share/libjpeg-turbo/libjpeg-turboConfigVersion.cmake",
      "SPDXID": "SPDXRef-binary-file-25",
      "checksums": [
        {
          "algorithm": "SHA256",
          "checksumValue": "5f50721998d8a027d988d80792cad3d49d8aae2b0c9dda86cc94958ade8b3d8d"
        }
      ],
      "licenseConcluded": "NOASSERTION",
      "copyrightText": "NOASSERTION"
    },
    {
      "fileName": "./share/libjpeg-turbo/libjpeg-turboTargets-debug.cmake",
      "SPDXID": "SPDXRef-binary-file-26",
      "checksums": [
        {
          "algorithm": "SHA256",
          "checksumValue": "28dd27e6c00da3989c1626adc5d4f9554be6e8bc02c8175175db8d488a85cc07"
        }
      ],
      "licenseConcluded": "NOASSERTION",
      "copyrightText": "NOASSERTION"
    },
    {
      "fileName": "./share/libjpeg-turbo/libjpeg-turboTargets-release.cmake",
      "SPDXID": "SPDXRef-binary-file-27",
      "checksums": [
        {
          "algorithm": "SHA256",
          "checksumValue": "61c549157cf284c7e70862e828207d1edeb4d26ed81d36c7e89b0643171a6e77"
        }
      ],
      "licenseConcluded": "NOASSERTION",
      "copyrightText": "NOASSERTION"
    },
    {
      "fileName": "./share/libjpeg-turbo/libjpeg-turboTargets.cmake",
      "SPDXID": "SPDXRef-binary-file-28",
      "checksums": [
        {
          "algorithm": "SHA256",
          "checksumValue": "c2d855a44f23e6b8a6ab5387784e94074a2cab15cd9bcef0d84264ca064fe624"
        }
      ],
      "licenseConcluded": "NOASSERTION",
      "copyrightText": "NOASSERTION"
    },
    {
      "fileName": "./share/libjpeg-turbo/usage",
      "SPDXID": "SPDXRef-binary-file-29",
      "checksums": [
        {
          "algorithm": "SHA256",
          "checksumValue": "f6ff243d0aba5bc85904527de17fc8a341a3568b0b19e3ac63b95029125b9e68"
        }
      ],
      "licenseConcluded": "NOASSERTION",
      "copyrightText": "NOASSERTION"
    }
  ]
}
